minGRU_pytorch/__init__.py
minGRU_pytorch/hybrid.py
minGRU_pytorch/hybridLM.py
minGRU_pytorch/minGRU.py
minGRU_pytorch/minLM.py
minGRU_pytorch/minLSTM.py
mingru_pytorch-0.2.0.dist-info/METADATA
mingru_pytorch-0.2.0.dist-info/WHEEL
mingru_pytorch-0.2.0.dist-info/licenses/LICENSE
mingru_pytorch-0.2.0.dist-info/RECORD
